icoscp/__init__.py
icoscp/const.py
icoscp/dobj.py
icoscp/exceptions.py
icoscp/header.md
icoscp/licence.pdf
icoscp/collection/__init__.py
icoscp/collection/collection.py
icoscp/cpauth/__init__.py
icoscp/cpauth/authentication.py
icoscp/cpb/__init__.py
icoscp/cpb/dobj.py
icoscp/cpb/dtype.py
icoscp/cpb/get_size.py
icoscp/cpb/logfile.py
icoscp/cpb/metadata.py
icoscp/sparql/__init__.py
icoscp/sparql/runsparql.py
icoscp/sparql/sparqls.py
icoscp/station/__init__.py
icoscp/station/fmap.py
icoscp/station/station.py
icoscp/stilt/__init__.py
icoscp-0.2.2.dist-info/METADATA
icoscp-0.2.2.dist-info/WHEEL
icoscp-0.2.2.dist-info/licenses/LICENSE
icoscp-0.2.2.dist-info/RECORD
