Metadata-Version: 2.3
Name: icoscp
Version: 0.2.2
Summary: Access to ICOS data objects hosted at https://data.icos-cp.eu
Project-URL: Homepage, https://www.icos-cp.eu/
Project-URL: Source, https://github.com/ICOS-Carbon-Portal/pylib/icoscp
Project-URL: Documentation, https://icos-carbon-portal.github.io/pylib/icoscp/
Project-URL: DataPortal, https://data.icos-cp.eu/portal/
Project-URL: SparqlEndpoint, https://meta.icos-cp.eu/sparqlclient/?type=CSV
Author-email: Claudio D'Onofrio <claudio.donofrio@nateko.lu.se>, Zois Zogopoulos <zois.zogopoulos@nateko.lu.se>, Anders Dahlner <anders.dahlner@nateko.lu.se>, Klara Broman <klara.broman@nateko.lu.se>, Oleg Mirzov <oleg.mirzov@nateko.lu.se>, ICOS Carbon Portal <info@icos-cp.eu>
License-File: LICENSE
Classifier: Development Status :: 4 - Beta
Classifier: Intended Audience :: Developers
Classifier: Intended Audience :: Education
Classifier: Intended Audience :: End Users/Desktop
Classifier: Intended Audience :: Science/Research
Classifier: License :: OSI Approved :: GNU General Public License v3 or later (GPLv3+)
Classifier: Natural Language :: English
Classifier: Operating System :: OS Independent
Classifier: Programming Language :: Python :: 3
Classifier: Topic :: Scientific/Engineering :: Atmospheric Science
Classifier: Topic :: Scientific/Engineering :: GIS
Classifier: Topic :: Scientific/Engineering :: Information Analysis
Classifier: Topic :: Scientific/Engineering :: Visualization
Classifier: Topic :: Utilities
Requires-Python: >=3.10
Requires-Dist: folium>=0.13.0
Requires-Dist: icoscp-core
Requires-Dist: pandas<=2.2.3,>=1.3.5
Requires-Dist: requests>=2.26.0
Requires-Dist: tqdm>=4.64.1
